{
	"credit": "Made with Blockbench, a free, modern block model editor by JannisX11",
	"parent": "item/ball_parent",
	"ambientocclusion": false,
	"textures": {
		"0": "3d_misc/3d_chorus_fruit",
		"1": "3d_misc/3d_chorus_fruit_1",
		"particle": "3d_misc/3d_chorus_fruit"
	},
	"elements": [
		{
			"name": "cube",
			"from": [6, 4.528846153846153, 6],
			"to": [10, 8.528846153846153, 10],
			"faces": {
				"north": {
					"uv": [
						6,
						5.768453788272183,
						10,
						9.768453788272183
					],
					"texture": "#0"
				},
				"east": {
					"uv": [
						10,
						9.768453788272183,
						6,
						5.768453788272183
					],
					"texture": "#0"
				},
				"south": {
					"uv": [
						6,
						5.768453788272183,
						10,
						9.768453788272183
					],
					"texture": "#0"
				},
				"west": {
					"uv": [
						6,
						5.768453788272183,
						10,
						9.768453788272183
					],
					"texture": "#0"
				},
				"up": {"uv": [6, 6, 10, 10], "texture": "#0"},
				"down": {"uv": [6, 6, 10, 10], "texture": "#0"}
			},
			"type": "cube"
		},
		{
			"name": "cube",
			"from": [6.5, 5.028846153846153, 5.5],
			"to": [9.5, 8.028846153846153, 6.5],
			"faces": {
				"north": {
					"uv": [
						6.5,
						6.268453788272183,
						9.5,
						9.268453788272183
					],
					"texture": "#0"
				},
				"east": {
					"uv": [
						10.5,
						9.268453788272183,
						9.5,
						6.268453788272183
					],
					"texture": "#0"
				},
				"south": {
					"uv": [
						6.5,
						6.268453788272183,
						9.5,
						9.268453788272183
					],
					"texture": "#0"
				},
				"west": {
					"uv": [
						5.5,
						6.268453788272183,
						6.5,
						9.268453788272183
					],
					"texture": "#0"
				},
				"up": {"uv": [6.5, 5.5, 9.5, 6.5], "texture": "#0"},
				"down": {
					"uv": [6.5, 9.5, 9.5, 10.5],
					"texture": "#0"
				}
			},
			"type": "cube"
		},
		{
			"name": "cube",
			"from": [6.5, 5.028846153846153, 9.5],
			"to": [9.5, 8.028846153846153, 10.5],
			"faces": {
				"north": {
					"uv": [
						6.5,
						6.268453788272183,
						9.5,
						9.268453788272183
					],
					"texture": "#0"
				},
				"east": {
					"uv": [
						6.5,
						9.268453788272183,
						5.5,
						6.268453788272183
					],
					"texture": "#0"
				},
				"south": {
					"uv": [
						6.5,
						6.268453788272183,
						9.5,
						9.268453788272183
					],
					"texture": "#0"
				},
				"west": {
					"uv": [
						9.5,
						6.268453788272183,
						10.5,
						9.268453788272183
					],
					"texture": "#0"
				},
				"up": {
					"uv": [6.5, 9.5, 9.5, 10.5],
					"texture": "#0"
				},
				"down": {
					"uv": [6.5, 5.5, 9.5, 6.5],
					"texture": "#0"
				}
			},
			"type": "cube"
		},
		{
			"name": "cube",
			"from": [5.5, 5.028846153846153, 6.5],
			"to": [6.5, 8.028846153846153, 9.5],
			"faces": {
				"north": {
					"uv": [
						9.5,
						6.268453788272183,
						10.5,
						9.268453788272183
					],
					"texture": "#0"
				},
				"east": {
					"uv": [
						9.5,
						9.268453788272183,
						6.5,
						6.268453788272183
					],
					"texture": "#0"
				},
				"south": {
					"uv": [
						5.5,
						6.268453788272183,
						6.5,
						9.268453788272183
					],
					"texture": "#0"
				},
				"west": {
					"uv": [
						6.5,
						6.268453788272183,
						9.5,
						9.268453788272183
					],
					"texture": "#0"
				},
				"up": {"uv": [5.5, 6.5, 6.5, 9.5], "texture": "#0"},
				"down": {
					"uv": [5.5, 6.5, 6.5, 9.5],
					"texture": "#0"
				}
			},
			"type": "cube"
		},
		{
			"name": "cube",
			"from": [9.5, 5.028846153846153, 6.5],
			"to": [10.5, 8.028846153846153, 9.5],
			"faces": {
				"north": {
					"uv": [
						5.5,
						6.268453788272183,
						6.5,
						9.268453788272183
					],
					"texture": "#0"
				},
				"east": {
					"uv": [
						9.5,
						9.268453788272183,
						6.5,
						6.268453788272183
					],
					"texture": "#0"
				},
				"south": {
					"uv": [
						9.5,
						6.268453788272183,
						10.5,
						9.268453788272183
					],
					"texture": "#0"
				},
				"west": {
					"uv": [
						6.5,
						6.268453788272183,
						9.5,
						9.268453788272183
					],
					"texture": "#0"
				},
				"up": {
					"uv": [9.5, 6.5, 10.5, 9.5],
					"texture": "#0"
				},
				"down": {
					"uv": [9.5, 6.5, 10.5, 9.5],
					"texture": "#0"
				}
			},
			"type": "cube"
		},
		{
			"name": "cube",
			"from": [6.5, 8.028846153846153, 6.5],
			"to": [9.5, 9.028846153846153, 9.5],
			"faces": {
				"north": {
					"uv": [
						6.5,
						5.268453788272183,
						9.5,
						6.268453788272183
					],
					"texture": "#0"
				},
				"east": {
					"uv": [
						9.5,
						6.268453788272183,
						6.5,
						5.268453788272183
					],
					"texture": "#0"
				},
				"south": {
					"uv": [
						6.5,
						5.268453788272183,
						9.5,
						6.268453788272183
					],
					"texture": "#0"
				},
				"west": {
					"uv": [
						6.5,
						5.268453788272183,
						9.5,
						6.268453788272183
					],
					"texture": "#0"
				},
				"up": {"uv": [6.5, 6.5, 9.5, 9.5], "texture": "#0"},
				"down": {
					"uv": [6.5, 6.5, 9.5, 9.5],
					"texture": "#0"
				}
			},
			"type": "cube"
		},
		{
			"name": "cube",
			"from": [6.5, 4.028846153846153, 6.5],
			"to": [9.5, 5.028846153846153, 9.5],
			"faces": {
				"north": {
					"uv": [
						6.5,
						9.268453788272183,
						9.5,
						10.268453788272183
					],
					"texture": "#0"
				},
				"east": {
					"uv": [
						9.5,
						10.268453788272183,
						6.5,
						9.268453788272183
					],
					"texture": "#0"
				},
				"south": {
					"uv": [
						6.5,
						9.268453788272183,
						9.5,
						10.268453788272183
					],
					"texture": "#0"
				},
				"west": {
					"uv": [
						6.5,
						9.268453788272183,
						9.5,
						10.268453788272183
					],
					"texture": "#0"
				},
				"up": {"uv": [6.5, 6.5, 9.5, 9.5], "texture": "#0"},
				"down": {
					"uv": [6.5, 6.5, 9.5, 9.5],
					"texture": "#0"
				}
			},
			"type": "cube"
		},
		{
			"name": "cube",
			"from": [7, 8.153846153846153, 7],
			"to": [9, 9.153846153846153, 9],
			"faces": {
				"north": {
					"uv": [7, 5.375, 9, 6.375],
					"texture": "#1"
				},
				"east": {
					"uv": [9, 6.375, 7, 5.375],
					"texture": "#1"
				},
				"south": {
					"uv": [7, 5.375, 9, 6.375],
					"texture": "#1"
				},
				"west": {
					"uv": [7, 5.375, 9, 6.375],
					"texture": "#1"
				},
				"up": {"uv": [7, 7, 9, 9], "texture": "#1"},
				"down": {"uv": [7, 7, 9, 9], "texture": "#1"}
			},
			"type": "cube"
		},
		{
			"name": "cube",
			"from": [7.5, 8.528846153846153, 7.5],
			"to": [8.5, 9.528846153846153, 8.5],
			"faces": {
				"north": {"uv": [7.5, 5, 8.5, 6], "texture": "#1"},
				"east": {"uv": [8.5, 6, 7.5, 5], "texture": "#1"},
				"south": {"uv": [7.5, 5, 8.5, 6], "texture": "#1"},
				"west": {"uv": [7.5, 5, 8.5, 6], "texture": "#1"},
				"up": {"uv": [7.5, 7.5, 8.5, 8.5], "texture": "#1"},
				"down": {
					"uv": [7.5, 7.5, 8.5, 8.5],
					"texture": "#1"
				}
			},
			"type": "cube"
		},
		{
			"name": "cube",
			"from": [7.5, 9.403846153846153, 6.5],
			"to": [8.5, 10.903846153846153, 7.5],
			"faces": {
				"north": {
					"uv": [7.5, 3.625, 8.5, 5.125],
					"texture": "#1"
				},
				"east": {
					"uv": [9.5, 5.125, 8.5, 3.625],
					"texture": "#1"
				},
				"south": {
					"uv": [7.5, 3.625, 8.5, 5.125],
					"texture": "#1"
				},
				"west": {
					"uv": [6.5, 3.625, 7.5, 5.125],
					"texture": "#1"
				},
				"up": {"uv": [7.5, 6.5, 8.5, 7.5], "texture": "#1"},
				"down": {
					"uv": [7.5, 8.5, 8.5, 9.5],
					"texture": "#1"
				}
			},
			"type": "cube"
		},
		{
			"name": "cube",
			"from": [7.5, 9.403846153846153, 8.5],
			"to": [8.5, 10.903846153846153, 9.5],
			"faces": {
				"north": {
					"uv": [7.5, 3.625, 8.5, 5.125],
					"texture": "#1"
				},
				"east": {
					"uv": [7.5, 5.125, 6.5, 3.625],
					"texture": "#1"
				},
				"south": {
					"uv": [7.5, 3.625, 8.5, 5.125],
					"texture": "#1"
				},
				"west": {
					"uv": [8.5, 3.625, 9.5, 5.125],
					"texture": "#1"
				},
				"up": {"uv": [7.5, 8.5, 8.5, 9.5], "texture": "#1"},
				"down": {
					"uv": [7.5, 6.5, 8.5, 7.5],
					"texture": "#1"
				}
			},
			"type": "cube"
		},
		{
			"name": "cube",
			"from": [6.5, 9.403846153846153, 7.5],
			"to": [7.5, 10.903846153846153, 8.5],
			"faces": {
				"north": {
					"uv": [8.5, 3.625, 9.5, 5.125],
					"texture": "#1"
				},
				"east": {
					"uv": [8.5, 5.125, 7.5, 3.625],
					"texture": "#1"
				},
				"south": {
					"uv": [6.5, 3.625, 7.5, 5.125],
					"texture": "#1"
				},
				"west": {
					"uv": [7.5, 3.625, 8.5, 5.125],
					"texture": "#1"
				},
				"up": {"uv": [6.5, 7.5, 7.5, 8.5], "texture": "#1"},
				"down": {
					"uv": [6.5, 7.5, 7.5, 8.5],
					"texture": "#1"
				}
			},
			"type": "cube"
		},
		{
			"name": "cube",
			"from": [8.5, 9.403846153846153, 7.5],
			"to": [9.5, 10.903846153846153, 8.5],
			"faces": {
				"north": {
					"uv": [6.5, 3.625, 7.5, 5.125],
					"texture": "#1"
				},
				"east": {
					"uv": [8.5, 5.125, 7.5, 3.625],
					"texture": "#1"
				},
				"south": {
					"uv": [8.5, 3.625, 9.5, 5.125],
					"texture": "#1"
				},
				"west": {
					"uv": [7.5, 3.625, 8.5, 5.125],
					"texture": "#1"
				},
				"up": {"uv": [8.5, 7.5, 9.5, 8.5], "texture": "#1"},
				"down": {
					"uv": [8.5, 7.5, 9.5, 8.5],
					"texture": "#1"
				}
			},
			"type": "cube"
		}
	],
	"display": {
		"gui": {
			"scale": [1.9, 1.9, 1.9],
			"rotation": [30, 45, 13],
			"translation": [0, 1, 0]
		}
	}
}